autocompletefilter/__init__.py
autocompletefilter/admin.py
autocompletefilter/filters.py
autocompletefilter/static/admin/js/autocomplete_filter.js
autocompletefilter/templates/admin/filter_autocomplete.html
django_autocompletefilter-0.0.9.dist-info/LICENSE
django_autocompletefilter-0.0.9.dist-info/METADATA
django_autocompletefilter-0.0.9.dist-info/WHEEL
django_autocompletefilter-0.0.9.dist-info/top_level.txt
django_autocompletefilter-0.0.9.dist-info/RECORD
