Metadata-Version: 2.1
Name: django-autocompletefilter
Version: 0.0.9
Summary: Django ModelAdmin list_filter with autocomplete widget.
Home-page: https://github.com/julianwachholz/django-autocompletefilter
Author: Julian Wachholz
Author-email: julian@wachholz.ch
License: MIT
Keywords: django django-admin autocomplete auto-complete filter select2
Classifier: Development Status :: 4 - Beta
Classifier: Environment :: Web Environment
Classifier: Framework :: Django
Classifier: Framework :: Django :: 2.0
Classifier: Framework :: Django :: 2.1
Classifier: Framework :: Django :: 2.2
Classifier: Framework :: Django :: 3.0
Classifier: Framework :: Django :: 3.1
Classifier: Framework :: Django :: 3.2
Classifier: Framework :: Django :: 4.0
Classifier: Framework :: Django :: 4.1
Classifier: Framework :: Django :: 4.2
Classifier: Framework :: Django :: 5.0
Classifier: Framework :: Django :: 5.1
Classifier: Intended Audience :: Developers
Classifier: License :: OSI Approved :: MIT License
Classifier: Programming Language :: Python
Classifier: Programming Language :: Python :: 3
Classifier: Programming Language :: Python :: 3 :: Only
Requires-Python: >=3.4
License-File: LICENSE
Requires-Dist: Django >=2.0
